AUTHORS
ChangeLog
LICENSE
Makefile
README-PYPI.md
README.md
TODO
requirements.txt
setup.cfg
setup.py
test-requirements.txt
tox.ini
docs/commands.md
docs/pyrene.png
docs/pyrene.svg
pyrene/__init__.py
pyrene/constants.py
pyrene/main.py
pyrene/network.py
pyrene/repos.py
pyrene/shell.py
pyrene/util.py
pyrene.egg-info/PKG-INFO
pyrene.egg-info/SOURCES.txt
pyrene.egg-info/dependency_links.txt
pyrene.egg-info/entry_points.txt
pyrene.egg-info/not-zip-safe
pyrene.egg-info/requires.txt
pyrene.egg-info/top_level.txt
pyrene/tests/__init__.py
pyrene/tests/test_main.py
pyrene/tests/test_network.py
pyrene/tests/test_repos.py
pyrene/tests/test_shell.py
pyrene/tests/test_util.py
pyrene/tests/util.py