Metadata-Version: 1.1
Name: pyrene
Version: 0.2
Summary: Copy packages between python package repositories & more
Home-page: https://github.com/krisztianfekete/pyrene
Author: Krisztián Fekete
Author-email: fekete.krisztyan@gmail.com
License: MIT
Keywords: pypi pip repository upload copy serve
Platform: UNKNOWN
Classifier: Development Status :: 4 - Beta
Classifier: Intended Audience :: Developers
Classifier: Environment :: Console
Classifier: Operating System :: POSIX
Classifier: License :: OSI Approved
Classifier: Programming Language :: Python
Classifier: Topic :: Utilities
Classifier: Topic :: System :: Archiving :: Packaging
Classifier: Topic :: System :: Installation/Setup
